pyroj/__init__.py
pyroj/rojjmer.py
pyroj-0.0.3.dist-info/LICENSE
pyroj-0.0.3.dist-info/METADATA
pyroj-0.0.3.dist-info/WHEEL
pyroj-0.0.3.dist-info/top_level.txt
pyroj-0.0.3.dist-info/RECORD
